main.py
mcp_server_mas_sequential_thinking-0.2.3.dist-info/METADATA
mcp_server_mas_sequential_thinking-0.2.3.dist-info/WHEEL
mcp_server_mas_sequential_thinking-0.2.3.dist-info/entry_points.txt
mcp_server_mas_sequential_thinking-0.2.3.dist-info/RECORD
