Metadata-Version: 2.4
Name: mcp-server-mas-sequential-thinking
Version: 0.2.3
Summary: MCP Agent Implementation for Sequential Thinking
Author-email: Frad LEE <fradser@gmail.com>
Requires-Python: >=3.10
Requires-Dist: agno
Requires-Dist: asyncio
Requires-Dist: exa-py
Requires-Dist: groq
Requires-Dist: mcp
Requires-Dist: python-dotenv
Provides-Extra: dev
Requires-Dist: black; extra == 'dev'
Requires-Dist: isort; extra == 'dev'
Requires-Dist: mypy; extra == 'dev'
Requires-Dist: pytest; extra == 'dev'
